{
  "type": "minecraft:chest",
  "pools": [
    {
      "rolls": {
		  "min": 1,
		  "max": 2
	  },
      "entries": [
        {
          "type": "minecraft:item",
          "name": "minecraft:dark_oak_log",
		  "weight": 10,
          "functions": [
            {
              "function": "minecraft:set_count",
              "count": {
                "type": "minecraft:uniform",
                "min": 1,
                "max": 16
              },
              "add": true
            }
          ]
        },
		{
          "type": "minecraft:item",
          "name": "minecraft:dark_oak_planks",
		  "weight": 10,
          "functions": [
            {
              "function": "minecraft:set_count",
              "count": {
                "type": "minecraft:uniform",
                "min": 1,
                "max": 48
              },
              "add": true
            }
          ]
        },
		{
          "type": "minecraft:item",
          "name": "minecraft:cooked_beef",
		  "weight": 1,
          "functions": [
            {
              "function": "minecraft:set_count",
              "count": {
                "type": "minecraft:uniform",
                "min": 1,
                "max": 16
              },
              "add": true
            }
          ]
        },
		{
          "type": "minecraft:item",
          "name": "minecraft:cooked_porkchop",
		  "weight": 1,
          "functions": [
            {
              "function": "minecraft:set_count",
              "count": {
                "type": "minecraft:uniform",
                "min": 1,
                "max": 16
              },
              "add": true
            }
          ]
        },
		{
          "type": "minecraft:item",
          "name": "minecraft:cooked_chicken",
		  "weight": 1,
          "functions": [
            {
              "function": "minecraft:set_count",
              "count": {
                "type": "minecraft:uniform",
                "min": 1,
                "max": 16
              },
              "add": true
            }
          ]
        },
		{
          "type": "minecraft:item",
          "name": "minecraft:cooked_rabbit",
		  "weight": 1,
          "functions": [
            {
              "function": "minecraft:set_count",
              "count": {
                "type": "minecraft:uniform",
                "min": 1,
                "max": 16
              },
              "add": true
            }
          ]
        },
		{
          "type": "minecraft:item",
          "name": "minecraft:cooked_mutton",
		  "weight": 1,
          "functions": [
            {
              "function": "minecraft:set_count",
              "count": {
                "type": "minecraft:uniform",
                "min": 1,
                "max": 16
              },
              "add": true
            }
          ]
        },
		{
          "type": "minecraft:item",
          "name": "minecraft:cooked_cod",
		  "weight": 1,
          "functions": [
            {
              "function": "minecraft:set_count",
              "count": {
                "type": "minecraft:uniform",
                "min": 1,
                "max": 16
              },
              "add": true
            }
          ]
        },
		{
          "type": "minecraft:item",
          "name": "minecraft:cooked_salmon",
		  "weight": 1,
          "functions": [
            {
              "function": "minecraft:set_count",
              "count": {
                "type": "minecraft:uniform",
                "min": 1,
                "max": 16
              },
              "add": true
            }
          ]
        },
		{
          "type": "minecraft:item",
          "name": "minecraft:iron_pickaxe",
		  "weight": 1,
          "functions": [
            {
              "function": "minecraft:set_count",
              "count": 1,
              "add": true
            },
            {
              "add": false,
              "damage": {
                "type": "minecraft:uniform",
                "max": 1,
                "min": 0.4
              },
              "function": "minecraft:set_damage"
            }
          ]
        },
		{
          "type": "minecraft:item",
          "name": "minecraft:iron_axe",
		  "weight": 1,
          "functions": [
            {
              "function": "minecraft:set_count",
              "count": 1,
              "add": true
            },
            {
              "add": false,
              "damage": {
                "type": "minecraft:uniform",
                "max": 1,
                "min": 0.4
              },
              "function": "minecraft:set_damage"
            }
          ]
        },
		{
          "type": "minecraft:item",
          "name": "minecraft:crossbow",
		  "weight": 1,
          "functions": [
            {
              "function": "minecraft:set_count",
              "count": 1,
              "add": true
            },
            {
              "add": false,
              "damage": {
                "type": "minecraft:uniform",
                "max": 1,
                "min": 0.4
              },
              "function": "minecraft:set_damage"
            }
          ]
        },
		{
          "type": "minecraft:item",
          "name": "minecraft:arrow",
		  "weight": 1,
          "functions": [
            {
              "function": "minecraft:set_count",
              "count": {
                "type": "minecraft:uniform",
                "min": 1,
                "max": 48
              },
              "add": true
            }
          ]
        },
		{
          "type": "minecraft:item",
          "name": "minecraft:light_blue_wool",
		  "weight": 5,
          "functions": [
            {
              "function": "minecraft:set_count",
              "count": {
                "type": "minecraft:uniform",
                "min": 1,
                "max": 48
              },
              "add": true
            }
          ]
        },
		{
          "type": "minecraft:item",
          "name": "minecraft:light_blue_carpet",
		  "weight": 2,
          "functions": [
            {
              "function": "minecraft:set_count",
              "count": {
                "type": "minecraft:uniform",
                "min": 1,
                "max": 48
              },
              "add": true
            }
          ]
        },
		{
          "type": "minecraft:item",
          "name": "minecraft:totem_of_undying",
		  "weight": 2,
          "functions": [
            {
              "function": "minecraft:set_count",
              "count": 1,
              "add": true
            }
          ]
        },
		{
          "type": "minecraft:item",
          "name": "minecraft:iron_ingot",
		  "weight": 2,
          "functions": [
            {
              "function": "minecraft:set_count",
              "count": {
                "type": "minecraft:uniform",
                "min": 1,
                "max": 24
              },
              "add": true
            }
          ]
        },
		{
          "type": "minecraft:item",
          "name": "minecraft:raw_gold",
		  "weight": 2,
          "functions": [
            {
              "function": "minecraft:set_count",
              "count": {
                "type": "minecraft:uniform",
                "min": 1,
                "max": 24
              },
              "add": true
            }
          ]
        },
		{
          "type": "minecraft:item",
          "name": "dndreams:snap_staff",
		  "weight": 2,
          "functions": [
            {
              "function": "minecraft:set_count",
              "count": 1,
              "add": true
            },
            {
              "add": false,
              "damage": {
                "type": "minecraft:uniform",
                "max": 1.0,
                "min": 0.5
              },
              "function": "minecraft:set_damage"
            }
          ]
        }
      ]
    }
  ]
}
